test/__init__.py
test/problem.py
test/settings.py
test/utils.py
test/extensions/__init__.py
test/extensions/firstorder/__init__.py
test/extensions/firstorder/batch_grad/__init__.py
test/extensions/firstorder/batch_grad/test_gram_batch_grad.py
test/extensions/secondorder/__init__.py
test/extensions/secondorder/sqrt_ggn/__init__.py
test/extensions/secondorder/sqrt_ggn/test_gram_sqrt_ggn.py
test/extensions/secondorder/vivit/__init__.py
test/extensions/secondorder/vivit/test_vivit_ggn.py
test/hessianfree/__init__.py
test/hessianfree/test___init__.py
test/implementation/__init__.py
test/implementation/autograd.py
test/implementation/backpack.py
test/implementation/base.py
test/implementation/linalg_autograd.py
test/implementation/linalg_backpack.py
test/implementation/optim_autograd.py
test/implementation/optim_backpack.py
test/implementation/test_autograd.py
test/linalg/__init__.py
test/linalg/settings.py
test/linalg/test_eigh.py
test/linalg/test_eigvalsh.py
test/optim/__init__.py
test/optim/settings.py
test/optim/test_directional_damped_newton.py
test/optim/test_directional_derivatives.py
test/utils/tensor_causes_symeig_error.pt
test/utils/test_checks.py
test/utils/test_stable_symeig.py
vivit/__init__.py
vivit/extensions/__init__.py
vivit/extensions/hooks.py
vivit/extensions/firstorder/__init__.py
vivit/extensions/firstorder/batch_grad/__init__.py
vivit/extensions/firstorder/batch_grad/gram_batch_grad.py
vivit/extensions/secondorder/__init__.py
vivit/extensions/secondorder/sqrt_ggn/__init__.py
vivit/extensions/secondorder/sqrt_ggn/gram_sqrt_ggn.py
vivit/extensions/secondorder/vivit/__init__.py
vivit/extensions/secondorder/vivit/base.py
vivit/extensions/secondorder/vivit/batchnormnd.py
vivit/extensions/secondorder/vivit/convnd.py
vivit/extensions/secondorder/vivit/convtransposend.py
vivit/extensions/secondorder/vivit/linear.py
vivit/hessianfree/__init__.py
vivit/hessianfree/lanczos.py
vivit/hessianfree/utils.py
vivit/linalg/__init__.py
vivit/linalg/eigh.py
vivit_for_pytorch-1.0.0.dist-info/LICENSE
vivit_for_pytorch-1.0.0.dist-info/METADATA
vivit_for_pytorch-1.0.0.dist-info/WHEEL
vivit_for_pytorch-1.0.0.dist-info/top_level.txt
vivit_for_pytorch-1.0.0.dist-info/RECORD
