Metadata-Version: 2.1
Name: vivit-for-pytorch
Version: 1.0.0
Summary: ViViT: Curvature access through the generalized Gauss-Newton\'s low-rank structure
Home-page: https://github.com/f-dangel/vivit
Author: Felix Dangel, Lukas Tatzel
License: MIT
Platform: any
Classifier: Development Status :: 4 - Beta
Classifier: License :: OSI Approved :: MIT License
Classifier: Operating System :: OS Independent
Classifier: Programming Language :: Python :: 3.8
Classifier: Programming Language :: Python :: 3.9
Requires-Python: >=3.7
License-File: LICENSE
Requires-Dist: backpack-for-pytorch (<2.0.0,>=1.5.0)
Requires-Dist: scipy (<2.0.0,>=1.7.1)
Requires-Dist: tqdm (<5.0.0,>=4.61.0)
Provides-Extra: docs
Requires-Dist: matplotlib ; extra == 'docs'
Requires-Dist: sphinx-gallery ; extra == 'docs'
Requires-Dist: sphinx-rtd-theme ; extra == 'docs'
Requires-Dist: functorch ; extra == 'docs'
Provides-Extra: lint
Requires-Dist: black ; extra == 'lint'
Requires-Dist: flake8 ; extra == 'lint'
Requires-Dist: mccabe ; extra == 'lint'
Requires-Dist: pycodestyle ; extra == 'lint'
Requires-Dist: pyflakes ; extra == 'lint'
Requires-Dist: pep8-naming ; extra == 'lint'
Requires-Dist: flake8-bugbear ; extra == 'lint'
Requires-Dist: flake8-comprehensions ; extra == 'lint'
Requires-Dist: flake8-tidy-imports ; extra == 'lint'
Requires-Dist: darglint ; extra == 'lint'
Requires-Dist: pydocstyle ; extra == 'lint'
Requires-Dist: isort ; extra == 'lint'
Provides-Extra: test
Requires-Dist: coveralls ; extra == 'test'
Requires-Dist: pytest ; extra == 'test'
Requires-Dist: pytest-cov ; extra == 'test'
